.bzrignore
COPYING
Changelog
MANIFEST.in
do_release.py
release.py
setup.py
setupegg.py
doc/Changelog.old
doc/DESIGN
doc/FORTRAN
doc/NOTES.txt
doc/THANKS.txt
doc/TODO
numscons/__init__.py
numscons/misc.py
numscons/testcode_snippets.py
numscons/version.py
numscons.egg-info/PKG-INFO
numscons.egg-info/SOURCES.txt
numscons.egg-info/dependency_links.txt
numscons.egg-info/top_level.txt
numscons/checkers/__init__.py
numscons/checkers/blas_lapack_checkers.py
numscons/checkers/checker_factory.py
numscons/checkers/common.py
numscons/checkers/configuration.py
numscons/checkers/fft_checkers.py
numscons/checkers/misc.py
numscons/checkers/perflib.cfg
numscons/checkers/perflib.py
numscons/checkers/perflib_config.py
numscons/checkers/perflib_info.py
numscons/checkers/simple_check.py
numscons/checkers/support.py
numscons/checkers/version_checkers.py
numscons/checkers/fortran/__init__.py
numscons/checkers/fortran/fortran.py
numscons/checkers/fortran/fortran_scons.py
numscons/core/__init__.py
numscons/core/allow_undefined.py
numscons/core/compiler_config.py
numscons/core/compiler_detection.py
numscons/core/custom_builders.py
numscons/core/customization.py
numscons/core/default.py
numscons/core/errors.py
numscons/core/extension_scons.py
numscons/core/helpers.py
numscons/core/initialization.py
numscons/core/misc.py
numscons/core/numpyenv.py
numscons/core/siteconfig.py
numscons/core/template_generators.py
numscons/core/trace.py
numscons/core/utils.py
numscons/core/configurations/compiler.cfg
numscons/core/configurations/cxxcompiler.cfg
numscons/core/configurations/fcompiler.cfg
numscons/numdist/__init__.py
numscons/numdist/conv_template.py
numscons/numdist/from_template.py
numscons/numdist/numdist_copy.py
numscons/scons-local/scons-LICENSE
numscons/scons-local/scons-README
numscons/scons-local/scons-time.py
numscons/scons-local/scons.py
numscons/scons-local/sconsign.py
numscons/scons-local/scons-local-1.2.0/SCons/Action.py
numscons/scons-local/scons-local-1.2.0/SCons/Builder.py
numscons/scons-local/scons-local-1.2.0/SCons/CacheDir.py
numscons/scons-local/scons-local-1.2.0/SCons/Conftest.py
