Metadata-Version: 1.0
Name: numscons
Version: 0.10.0
Summary: Enable to use scons within distutils to build extensions
Home-page: UNKNOWN
Author: David Cournapeau
Author-email: david@ar.media.kyoto-u.ac.jp
License: UNKNOWN
Platform: UNKNOWN
